AutoFeatures/AutoFeatures.py
AutoFeatures/__init__.py
AutoFeatures-1.0.2.dist-info/LICENSE
AutoFeatures-1.0.2.dist-info/METADATA
AutoFeatures-1.0.2.dist-info/WHEEL
AutoFeatures-1.0.2.dist-info/top_level.txt
AutoFeatures-1.0.2.dist-info/RECORD
